ngm/__about__.py
ngm/__init__.py
ngm/__main__.py
ngm/modules.json
ngm/ngm.py
nginx_manager-0.0.16.dist-info/LICENSE
nginx_manager-0.0.16.dist-info/METADATA
nginx_manager-0.0.16.dist-info/WHEEL
nginx_manager-0.0.16.dist-info/entry_points.txt
nginx_manager-0.0.16.dist-info/top_level.txt
nginx_manager-0.0.16.dist-info/RECORD
