Metadata-Version: 2.1
Name: nginx-manager
Version: 0.0.16
Summary: A CLI tool to manage NGINX configuration
Home-page: https://github.com/GetPageSpeed/ngm
Author: Danila Vershinin
Author-email: info@getpagespeed.com
License: BSD
Classifier: Intended Audience :: Developers
Classifier: Intended Audience :: System Administrators
Classifier: Operating System :: OS Independent
Classifier: Topic :: Software Development
License-File: LICENSE
Requires-Dist: argcomplete
Requires-Dist: tabulate
Requires-Dist: distro
Provides-Extra: dev
Requires-Dist: argcomplete ; extra == 'dev'
Requires-Dist: tabulate ; extra == 'dev'
Requires-Dist: distro ; extra == 'dev'
Requires-Dist: pyyaml ; extra == 'dev'
Provides-Extra: tests
Requires-Dist: argcomplete ; extra == 'tests'
Requires-Dist: tabulate ; extra == 'tests'
Requires-Dist: distro ; extra == 'tests'
Requires-Dist: pytest (>=4.4.0) ; extra == 'tests'
Requires-Dist: flake8 ; extra == 'tests'
Requires-Dist: pytest-xdist ; extra == 'tests'
